pytest_odoo_fixtures/__init__.py
pytest_odoo_fixtures/main.py
pytest_odoo_fixtures-0.1.dev0.dist-info/LICENSE
pytest_odoo_fixtures-0.1.dev0.dist-info/METADATA
pytest_odoo_fixtures-0.1.dev0.dist-info/WHEEL
pytest_odoo_fixtures-0.1.dev0.dist-info/top_level.txt
pytest_odoo_fixtures-0.1.dev0.dist-info/RECORD
