Metadata-Version: 2.1
Name: pytest-odoo-fixtures
Version: 0.1.dev0
Summary: Project description
Home-page: https://github.com/voronind/pytest-odoo-fixtures
Author: UNKNOWN
Author-email: dimka665@gmail.com
License: MIT License
Platform: UNKNOWN
Classifier: License :: OSI Approved :: MIT License
Classifier: Programming Language :: Python :: 2.7
Classifier: Programming Language :: Python :: 3 :: Only
Classifier: Programming Language :: Python :: Implementation :: PyPy
Classifier: Intended Audience :: Developers
Classifier: Topic :: Software Development :: Libraries :: Python Modules
